day_of_week_lib/__init__.py
day_of_week_lib/core.py
day_of_week_lib/main.py
dayofweeklib-0.1.0.dist-info/licenses/LICENSE
dayofweeklib-0.1.0.dist-info/METADATA
dayofweeklib-0.1.0.dist-info/WHEEL
dayofweeklib-0.1.0.dist-info/entry_points.txt
dayofweeklib-0.1.0.dist-info/top_level.txt
dayofweeklib-0.1.0.dist-info/RECORD
