Metadata-Version: 2.4
Name: DayOfWeekLib
Version: 0.1.0
Summary: Get day of the week from a date
Author: Nesma Mohamad  Al-Btry
Author-email: Nesma Mohamad  Al-Btry <nasmhalbtri23@gmail.com>
License: MIT License
Requires-Python: >=3.7
License-File: LICENSE
Dynamic: author
Dynamic: license-file
Dynamic: requires-python
